LICENSE
MANIFEST.in
README.rst
setup.py
./extra_views/__init__.py
./extra_views/advanced.py
./extra_views/dates.py
./extra_views/formsets.py
./extra_views/generic.py
./extra_views/models.py
./extra_views/multi.py
./extra_views/search.py
./extra_views/sorting.py
django_extra_views_ng.egg-info/PKG-INFO
django_extra_views_ng.egg-info/SOURCES.txt
django_extra_views_ng.egg-info/dependency_links.txt
django_extra_views_ng.egg-info/top_level.txt