Metadata-Version: 1.1
Name: django-extra-views-ng
Version: 0.3.2
Summary: Extra class-based views for Django
Home-page: https://github.com/hovel/django-extra-views
Author: Pavel Zhukov
Author-email: gelios@gmail.com
License: MIT
Platform: UNKNOWN
Classifier: Development Status :: 5 - Production/Stable
Classifier: Environment :: Web Environment
Classifier: Framework :: Django
Classifier: Intended Audience :: Developers
Classifier: Programming Language :: Python
